{
    "map_key": "hub",
    "entities": {
        "AP_CHECK_GAME_PROGRESS_CODEX_1": 7770072,
        "AP_CHECK_PICKUP_EQUIPMENT_FLAME_BELCH_1": 7770073,
        "AP_CHECK_PICKUP_EQUIPMENT_ICE_BOMB": 7770074,
        "AP_CHECK_PROGRESS_ARGENT_CELL_1_1072112848": 7770086,
        "AP_CHECK_PROGRESS_ARGENT_CELL_1_750400652": 7770087,
        "AP_CHECK_PROGRESS_ARGENT_CELL_1_2075197287": 7770088,
        "AP_CHECK_PROGRESS_PRAETOR_POINT_HUB_1": 7770081,
        "AP_CHECK_SENTINEL_BATTERY_ROOM_PROGRESS_PRAETOR_TOKEN_1": 7770163,
        "AP_CHECK_SENTINEL_BATTERY_ROOM_PROGRESS_PRAETOR_TOKEN_2": 7770164,
        "AP_CHECK_SENTINEL_BATTERY_ROOM_PROGRESS_MOD_BOT_3": 7770165,
        "AP_CHECK_SENTINEL_BATTERY_ROOM_PROGRESS_MOD_BOT_4": 7770166,
        "AP_CHECK_PROGRESS_PRAETOR_TOKEN_3": 7770167,
        "AP_CHECK_PROGRESS_PRAETOR_TOKEN_4": 7770168,
        "AP_CHECK_PROGRESS_CHEATS_ALL_MASTERED_RUNES_1": 7770169,
        "AP_CHECK_PICKUP_WEAPON_GAUSS_RIFLE_HUB_1": 7770170,
        "AP_CHECK_PROGRESS_CHEATS_FULLY_UPGRADED_PROGRESSION_WHEEL_FINAL": 7770171
    },
    "target_removals": {
        "target_relay_pickup_ballista": [
            "target_give_item_ballista"
        ]
    },
    "remove_entities": [
        "target_give_item_ballista"
    ],
    "target_policies": {
        "pickup_equipment_flame_belch_1": {
            "independent_ap_trigger": true,
            "remove_original": true,
            "no_auto_visual": true,
            "preserve_targets": [
                "target_relay_pickup_flame_belch"
            ],
            "drop_targets": [
                "target_give_item_flame_belch"
            ]
        },
        "pickup_equipment_ice_bomb": {
            "independent_ap_trigger": true,
            "independent_position": [
                0.47,
                -22.27,
                -14.38
            ],
            "independent_size": [
                4.0,
                3.0,
                3.5
            ],
            "independent_visual": {
                "entity_name": "ap_location_visual_7770074",
                "cleanup_entity": "ap_remove_location_visual_7770074",
                "model": "art/pickups/question_mark_a.lwo",
                "thinkComponentDecl": "bob_rotate_fast",
                "position": [
                    0.47,
                    -22.27,
                    -15.38
                ],
                "scale": [
                    1.75,
                    1.75,
                    1.75
                ]
            },
            "drop_targets": [
                "target_give_item_ice_bomb"
            ]
        },
        "progress_argent_cell_1_1072112848": {
            "gate_relay": "target_relay_argent_cell_useable",
            "independent_ap_trigger": true,
            "remove_original": true
        },
        "progress_argent_cell_1_750400652": {
            "gate_relay": "target_relay_argent_cell_useable",
            "independent_ap_trigger": true,
            "remove_original": true
        },
        "progress_argent_cell_1_2075197287": {
            "gate_relay": "target_relay_argent_cell_useable",
            "independent_ap_trigger": true,
            "remove_original": true
        },
        "progress_praetor_point_hub_1": {
            "native_entity_contract": {
                "remove_block": "currencyList",
                "original_targets": [
                    "target_relay_complete_praetor_obj"
                ],
                "required_snippets": [
                    "\"game/sp/hub/from_e1m2\"",
                    "inherit = \"progress/praetor_token\";",
                    "class = \"idInteractable_GiveItems\";",
                    "saveType = \"SGS_GAME_DATA\";",
                    "automapPropertiesDecl = \"praetor_token\";",
                    "model = \"md6def/objects/interact/praetor_suit_token/praetor_suit_token.md6\";",
                    "stat = \"STAT_GAINED_FIRST_PRAETOR_TOKEN\";",
                    "onUseCodexEntry = \"codex/tutorials/praetor_suit_perks\";",
                    "progressionCategory = \"PROGRESSION_CATEGORY_ELITE\";",
                    "useStat = \"STAT_SUIT_PAGE_UNLOCKED\";",
                    "flags = {\n\t\t\thide = true;\n\t\t}"
                ]
            }
        },
        "sentinel_battery_room_progress_praetor_token_1": {
            "native_entity_contract": {
                "remove_block": "currencyList",
                "original_targets": ["sentinel_battery_room_target_relay_item_used1"],
                "required_snippets": [
                    "inherit = \"progress/praetor_token\";",
                    "class = \"idInteractable_GiveItems\";",
                    "saveType = \"SGS_GAME_DATA\";",
                    "automapPropertiesDecl = \"praetor_token\";",
                    "currencyType = \"CURRENCY_PRAETOR_UPGRADE\";"
                ]
            }
        },
        "sentinel_battery_room_progress_praetor_token_2": {
            "native_entity_contract": {
                "remove_block": "currencyList",
                "original_targets": ["sentinel_battery_room_target_relay_item_used2"],
                "required_snippets": [
                    "inherit = \"progress/praetor_token\";",
                    "class = \"idInteractable_GiveItems\";",
                    "saveType = \"SGS_GAME_DATA\";",
                    "automapPropertiesDecl = \"praetor_token\";",
                    "currencyType = \"CURRENCY_PRAETOR_UPGRADE\";"
                ]
            }
        },
        "sentinel_battery_room_progress_mod_bot_3": {
            "independent_ap_trigger": true,
            "remove_original": true,
            "preserve_targets": ["sentinel_battery_room_target_relay_item_used3"],
            "drop_targets": [],
            "safe_target_graph": {
                "sentinel_battery_room_target_relay_item_used3": []
            },
            "forbidden_target_terms": ["currency", "give", "grant", "inventory", "perk"]
        },
        "sentinel_battery_room_progress_mod_bot_4": {
            "independent_ap_trigger": true,
            "remove_original": true,
            "preserve_targets": ["sentinel_battery_room_target_relay_item_used"],
            "drop_targets": [],
            "safe_target_graph": {
                "sentinel_battery_room_target_relay_item_used": []
            },
            "forbidden_target_terms": ["currency", "give", "grant", "inventory", "perk"]
        },
        "progress_praetor_token_3": {
            "native_entity_contract": {
                "remove_block": "currencyList",
                "original_targets": ["sentinel_battery_room_target_relay_item_used_24"],
                "required_snippets": [
                    "inherit = \"progress/praetor_token\";",
                    "class = \"idInteractable_GiveItems\";",
                    "saveType = \"SGS_GAME_DATA\";",
                    "automapPropertiesDecl = \"praetor_token\";",
                    "currencyType = \"CURRENCY_PRAETOR_UPGRADE\";"
                ]
            }
        },
        "progress_praetor_token_4": {
            "native_entity_contract": {
                "remove_block": "currencyList",
                "original_targets": ["sentinel_battery_room_target_relay_item_used_25"],
                "required_snippets": [
                    "inherit = \"progress/praetor_token\";",
                    "class = \"idInteractable_GiveItems\";",
                    "saveType = \"SGS_GAME_DATA\";",
                    "automapPropertiesDecl = \"praetor_token\";",
                    "currencyType = \"CURRENCY_PRAETOR_UPGRADE\";"
                ]
            }
        },
        "pickup_weapon_gauss_rifle_hub_1": {
            "independent_ap_trigger": true,
            "remove_original": true,
            "preserve_targets": ["target_relay_pickup_ballista"],
            "drop_targets": ["target_give_item_ballista"],
            "safe_target_graph": {
                "target_relay_pickup_ballista": ["target_relay_complete_ballista_obj"],
                "target_relay_complete_ballista_obj": ["target_objective_complete_ballista"],
                "target_objective_complete_ballista": []
            },
            "forbidden_target_terms": ["currency", "give", "grant", "inventory", "perk"]
        }
    }
}
